[
    {
        "key": "datr",
        "value": "W2oLaMVIXGDz_va5DMR9eK90",
        "domain": "facebook.com",
        "path": "/",
        "hostOnly": false,
        "creation": "2025-04-27T23:37:52.337Z",
        "lastAccessed": "2025-04-27T23:37:52.338Z"
    },
    {
        "key": "sb",
        "value": "W2oLaP_RyG0bSX6us7zBHPiv",
        "domain": "facebook.com",
        "path": "/",
        "hostOnly": false,
        "creation": "2025-04-27T23:37:52.338Z",
        "lastAccessed": "2025-04-27T23:37:52.338Z"
    },
    {
        "key": "locale",
        "value": "vi_VN",
        "domain": "facebook.com",
        "path": "/",
        "hostOnly": false,
        "creation": "2025-04-27T23:37:52.338Z",
        "lastAccessed": "2025-04-27T23:37:52.338Z"
    },
    {
        "key": "vpd",
        "value": "v1%3B694x360x2",
        "domain": "facebook.com",
        "path": "/",
        "hostOnly": false,
        "creation": "2025-04-27T23:37:52.338Z",
        "lastAccessed": "2025-04-27T23:37:52.338Z"
    },
    {
        "key": "ps_l",
        "value": "1",
        "domain": "facebook.com",
        "path": "/",
        "hostOnly": false,
        "creation": "2025-04-27T23:37:52.338Z",
        "lastAccessed": "2025-04-27T23:37:52.338Z"
    },
    {
        "key": "ps_n",
        "value": "1",
        "domain": "facebook.com",
        "path": "/",
        "hostOnly": false,
        "creation": "2025-04-27T23:37:52.338Z",
        "lastAccessed": "2025-04-27T23:37:52.338Z"
    },
    {
        "key": "m_pixel_ratio",
        "value": "2",
        "domain": "facebook.com",
        "path": "/",
        "hostOnly": false,
        "creation": "2025-04-27T23:37:52.338Z",
        "lastAccessed": "2025-04-27T23:37:52.338Z"
    },
    {
        "key": "c_user",
        "value": "61568220163458",
        "domain": "facebook.com",
        "path": "/",
        "hostOnly": false,
        "creation": "2025-04-27T23:37:52.338Z",
        "lastAccessed": "2025-04-27T23:37:52.338Z"
    },
    {
        "key": "fr",
        "value": "0uz8jdJsTNvwedyHV.AWeedolS8NFwj1gTR6WySnrnSFZsL6faG8gHe94HzPgHsxJXVXI.BoC2pb..AAA.0.0.BoDr-4.AWdbYczWQmPPYZhK2WPBE2Z1yHA",
        "domain": "facebook.com",
        "path": "/",
        "hostOnly": false,
        "creation": "2025-04-27T23:37:52.338Z",
        "lastAccessed": "2025-04-27T23:37:52.338Z"
    },
    {
        "key": "xs",
        "value": "28%3Alqgj6tCm_gnV8g%3A2%3A1745797048%3A-1%3A14169",
        "domain": "facebook.com",
        "path": "/",
        "hostOnly": false,
        "creation": "2025-04-27T23:37:52.338Z",
        "lastAccessed": "2025-04-27T23:37:52.338Z"
    },
    {
        "key": "wd",
        "value": "360x694",
        "domain": "facebook.com",
        "path": "/",
        "hostOnly": false,
        "creation": "2025-04-27T23:37:52.338Z",
        "lastAccessed": "2025-04-27T23:37:52.338Z"
    },
    {
        "key": "fbl_st",
        "value": "100732886%3BT%3A29096617",
        "domain": "facebook.com",
        "path": "/",
        "hostOnly": false,
        "creation": "2025-04-27T23:37:52.338Z",
        "lastAccessed": "2025-04-27T23:37:52.338Z"
    },
    {
        "key": "wl_cbv",
        "value": "v2%3Bclient_version%3A2801%3Btimestamp%3A1745797066",
        "domain": "facebook.com",
        "path": "/",
        "hostOnly": false,
        "creation": "2025-04-27T23:37:52.338Z",
        "lastAccessed": "2025-04-27T23:37:52.338Z"
    }
]
